nvidb/__init__.py
nvidb/config.py
nvidb/connection.py
nvidb/data_modules.py
nvidb/logger.py
nvidb/monitor.py
nvidb/utils.py
nvidb/web.py
nvidb/.streamlit/config.toml
nvidb/test/__init__.py
nvidb/test/run.py
nvidb-1.6.6.dist-info/licenses/LICENSE
nvidb-1.6.6.dist-info/METADATA
nvidb-1.6.6.dist-info/WHEEL
nvidb-1.6.6.dist-info/entry_points.txt
nvidb-1.6.6.dist-info/top_level.txt
nvidb-1.6.6.dist-info/RECORD
