Metadata-Version: 2.4
Name: nvidb
Version: 1.6.6
Summary: A package that provides an aggregated view of the NVIDIA GPU information on several hosts.
Author: L1ght
License-Expression: MIT
Project-URL: Homepage, https://github.com/FanBB2333/nvidb
Project-URL: Repository, https://github.com/FanBB2333/nvidb
Keywords: nvidia,gpu,monitoring,ssh,remote
Classifier: Development Status :: 4 - Beta
Classifier: Environment :: Console
Classifier: Intended Audience :: Developers
Classifier: Intended Audience :: System Administrators
Classifier: Operating System :: OS Independent
Classifier: Programming Language :: Python :: 3
Classifier: Programming Language :: Python :: 3.8
Classifier: Programming Language :: Python :: 3.9
Classifier: Programming Language :: Python :: 3.10
Classifier: Programming Language :: Python :: 3.11
Classifier: Programming Language :: Python :: 3.12
Classifier: Topic :: System :: Hardware
Classifier: Topic :: System :: Monitoring
Requires-Python: >=3.8
License-File: LICENSE
Requires-Dist: pandas
Requires-Dist: paramiko
Requires-Dist: PyYAML
Requires-Dist: termcolor
Requires-Dist: nvidia-ml-py
Requires-Dist: blessed
Provides-Extra: dev
Requires-Dist: pytest; extra == "dev"
Requires-Dist: setuptools; extra == "dev"
Dynamic: license-file
